players_yach/__init__.py
players_yach/scraper.py
players_ftbl12-0.0.6.dist-info/LICENCE.txt
players_ftbl12-0.0.6.dist-info/METADATA
players_ftbl12-0.0.6.dist-info/WHEEL
players_ftbl12-0.0.6.dist-info/top_level.txt
players_ftbl12-0.0.6.dist-info/RECORD
