Metadata-Version: 2.1
Name: players-ftbl12
Version: 0.0.6
Summary: Takes player information from Transfermarkt
Home-page: https://github.com/y1ach/playersftbl12
Author: Yach
Author-email: yigitalicelik@hotmail.com
Keywords: Football Players
Classifier: Development Status :: 5 - Production/Stable
Classifier: Intended Audience :: Education
Classifier: Operating System :: Microsoft :: Windows :: Windows 11
Classifier: Programming Language :: Python :: 3
Classifier: License :: OSI Approved :: MIT License
License-File: LICENCE.txt
Requires-Dist: requests
Requires-Dist: beautifulsoup4
